{
  "name": "@byted-lina/common-charts-option",
  "version": "1.1.2",
  "description": "通用图表数据",
  "maintainers": [
    "suhan.su"
  ],
  "main": "dist/index.js",
  "types": "dist/index.d.ts",
  "files": [
    "src",
    "dist"
  ],
  "scripts": {
    "build": "rm -rf dist && ttsc",
    "build:doc": "typedoc",
    "prepublish:only": "typedoc",
    "start": "ttsc -w",
    "test": "TZ=Asia/Shanghai jest",
    "test:type": "tsc --noemit"
  },
  "dependencies": {},
  "devDependencies": {
    "@types/jest": "^27.0.1",
    "jest": "^27.4.5",
    "ts-jest": "^27.1.2",
    "ts-node": "^10.5.0",
    "ttypescript": "^1.5.15",
    "typedoc": "^0.25.4",
    "typedoc-plugin-markdown": "^3.17.1",
    "typescript": "^4.5.2"
  },
  "tsup": {
    "entry": [
      "src/index.ts"
    ],
    "dts": true,
    "target": "node14",
    "sourcemap": true,
    "clean": true
  }
}